CHANGELOG.txt
LICENSE
MANIFEST.in
README.md
setup.py
arcangelai/__init__.py
arcangelai.egg-info/PKG-INFO
arcangelai.egg-info/SOURCES.txt
arcangelai.egg-info/dependency_links.txt
arcangelai.egg-info/top_level.txt