Metadata-Version: 2.1
Name: arcangelai
Version: 2.0.6
Summary: Autonomous AI
Home-page: 
Author: Arc Angel Ai
Author-email: info@arcangelai.com
License: MIT
Keywords: autonomous
Classifier: Development Status :: 5 - Production/Stable
Classifier: Intended Audience :: Education
Classifier: License :: OSI Approved :: MIT License
Classifier: Programming Language :: Python :: 3
License-File: LICENSE
